{
  "c_suite_explanations": {
    "self_titel": "Beteiligte im dualen System (Betrieb, Berufsschule, zustaendige Stelle, ggf. UEBS)",
    "self_subtitel": "WISO - Ausbildungsbetrieb & duales System",
    "self_message": "Hi, ich bin Beteiligte im dualen System. Ich trainiere Rollen, Kommunikationswege und Terminabstimmung zwischen den Akteuren.",
    "ceo_message": "Klar definierte Verantwortlichkeiten verhindern Reibung und machen Ausbildungsprozesse belastbar.",
    "coo_message": "Wenn Kommunikationspfade sauber eingehalten werden, sinken Eskalationsaufwand und Durchlaufzeit.",
    "cio_message": "Messwerte wie Rollen-Treffquote und Pfadgenauigkeit machen Lernfortschritt transparent.",
    "cfo_message": "Saubere Koordination zwischen den Lernorten senkt Fehlerkosten und reduziert Nacharbeit."
  },
  "Icon": "books"
}
