{
  "meta": {
    "topic": "Englisch",
    "mechanic": "simulation",
    "engine": "SimulationGame",
    "variant": "englisch",
    "version": "1.0"
  },
  "title": "Englisch - Parameter Simulation",
  "goal": {
    "targetRateEur": 484,
    "maxDownPaymentEur": 2900
  },
  "pricing": {
    "baseRate": 562,
    "termPerMonthDiscount": 1.9,
    "downPaymentPer100Discount": 1.9,
    "kmPer1000Surcharge": 14,
    "minRate": 148
  },
  "limits": {
    "termMonths": {
      "min": 12,
      "max": 66,
      "step": 6,
      "default": 18
    },
    "downPaymentEur": {
      "min": 0,
      "max": 5500,
      "step": 100,
      "default": 900
    },
    "kmPerYear": {
      "min": 5000,
      "max": 45000,
      "step": 1000,
      "default": 18000
    }
  }
}
