{
  "meta": {
    "topic": "Singleton Pattern",
    "mechanic": "decision_quiz",
    "engine": "DecisionGame",
    "source": "_gg01_singleton_challenge.json",
    "version": "2.0"
  },
  "title": "Singleton",
  "subtitle": "Waehle je Runde die fachlich beste Entscheidung.",
  "rounds": [
    {
      "id": 1,
      "phase": "Runde 1",
      "situation": "Global Logger",
      "options": [
        {
          "id": "a",
          "text": "Global Logger",
          "correct": true,
          "reason": "Die korrekte Option folgt direkt aus den vorliegenden Informationen."
        },
        {
          "id": "b",
          "text": "Nur nach Bauchgefuehl entscheiden",
          "correct": false,
          "reason": "Nicht die beste Wahl fuer das Szenario."
        },
        {
          "id": "c",
          "text": "Ohne Pruefung direkt festlegen",
          "correct": false,
          "reason": "Nicht die beste Wahl fuer das Szenario."
        }
      ]
    },
    {
      "id": 2,
      "phase": "Runde 2",
      "situation": "DB Connection Pool",
      "options": [
        {
          "id": "a",
          "text": "DB Connection Pool",
          "correct": true,
          "reason": "Die korrekte Option folgt direkt aus den vorliegenden Informationen."
        },
        {
          "id": "b",
          "text": "Nur nach Bauchgefuehl entscheiden",
          "correct": false,
          "reason": "Nicht die beste Wahl fuer das Szenario."
        },
        {
          "id": "c",
          "text": "Ohne Pruefung direkt festlegen",
          "correct": false,
          "reason": "Nicht die beste Wahl fuer das Szenario."
        }
      ]
    },
    {
      "id": 3,
      "phase": "Runde 3",
      "situation": "Game Configuration",
      "options": [
        {
          "id": "a",
          "text": "Game Configuration",
          "correct": true,
          "reason": "Die korrekte Option folgt direkt aus den vorliegenden Informationen."
        },
        {
          "id": "b",
          "text": "Nur nach Bauchgefuehl entscheiden",
          "correct": false,
          "reason": "Nicht die beste Wahl fuer das Szenario."
        },
        {
          "id": "c",
          "text": "Ohne Pruefung direkt festlegen",
          "correct": false,
          "reason": "Nicht die beste Wahl fuer das Szenario."
        }
      ]
    }
  ]
}
