{
  "c_suite_explanations": {
    "self_titel": "Kaufvertrag",
    "self_subtitel": "Eigentumsuebertragung gegen Gegenleistung",
    "self_message": "Hi, ich bin Kaufvertrag. Ich regle rechtlich verbindlich, wer was zu welchen Bedingungen liefert, bezahlt und im Streitfall verantwortet.",
    "ceo_message": "Fuer Kaufvertrag gilt: Ich brauche einen belastbaren Rahmen fuer Geschaeftsbeziehungen und Risikoallokation.",
    "cfo_message": "Fuer Kaufvertrag gilt: Ich schaue auf Haftungsfolgen, Zahlungsrisiken und wirtschaftliche Nebenklauseln.",
    "coo_message": "Fuer Kaufvertrag gilt: Ich pruefe die operative Umsetzbarkeit, um Reibung und Nacharbeit zu vermeiden.",
    "cio_message": "Ich verankere bei Kaufvertrag dokumentierte Nachweise, revisionssichere Ablage und konsistente Prozessdaten.",
    "ciso_message": "Ich pruefe bei Kaufvertrag Compliance, Datenschutz und risikorelevante Vertragsklauseln."
  }
}
