{
  "c_suite_explanations": {
    "self_titel": "IT-Sicherheit",
    "self_subtitel": "Ganzheitlicher Schutz von Systemen und Daten",
    "self_message": "Hi, ich bin IT-Sicherheit. Ich kombiniere Technik, Prozesse und Verhalten, um Angriffe zu erschweren und Auswirkungen zu begrenzen.",
    "ciso_message": "IT-Sicherheit ist ein Kernbaustein, um Schutzbedarf wirksam in konkrete Massnahmen zu ueberfuehren.",
    "cio_message": "Bei IT-Sicherheit muss Sicherheit im Betrieb praktikabel bleiben, sonst wird sie umgangen.",
    "clo_message": "IT-Sicherheit beruehrt Compliance und Nachweispflichten, die rechtssicher dokumentiert sein muessen.",
    "cro_message": "IT-Sicherheit wird ueber Eintrittswahrscheinlichkeit und Schadensausmass priorisiert gesteuert.",
    "cto_message": "IT-Sicherheit braucht technische Härtung, sichere Defaults und belastbare Architekturentscheidungen.",
    "cfo_message": "IT-Sicherheit ist wirtschaftlich relevant, weil praeventive Kontrolle guenstiger als Vorfallschaden ist."
  }
}
