{
  "gameId": "zielgruppen_radar",
  "title": "Zielgruppen-Radar",
  "description": "Passe den Präsentationsstil an die jeweilige Zielgruppe an.",
  "timing": {
    "default_round_ms": 18000
  },
  "scoring": {
    "correct": 25,
    "wrong": -8,
    "timeout": -10,
    "completion_bonus": 10
  },
  "audiences": [
    {
      "id": 1,
      "name": "Geschäftsführung",
      "context": "Kurzfristiges Steering-Meeting zur Projektfreigabe",
      "need": "entscheidungsreife Ergebnisse in kurzer Zeit",
      "correctStyleId": "b",
      "styles": [
        { "id": "a", "label": "Detailliert & technisch", "reason": "Zu tief im Detail für ein kurzes Entscheider-Meeting." },
        { "id": "b", "label": "Kurz & ergebnisorientiert", "reason": "Richtig: Fokus auf Optionen, Risiken und Entscheidungsvorlage." },
        { "id": "c", "label": "Lustig & verspielt", "reason": "Unterhaltsam, aber nicht passend für Board-Entscheidungen." }
      ]
    },
    {
      "id": 2,
      "name": "Azubi-Schulung",
      "context": "Einführung in neue Support-Prozesse",
      "need": "klare Erklärungen mit Beispielen und Motivation",
      "correctStyleId": "a",
      "styles": [
        { "id": "a", "label": "Didaktisch & schrittweise", "reason": "Richtig: Lernende profitieren von Struktur, Beispielen und Wiederholung." },
        { "id": "b", "label": "Nur KPI-Folien", "reason": "Zu abstrakt und wenig lernförderlich für Einsteiger." },
        { "id": "c", "label": "Nur Live-Demo ohne Erklärung", "reason": "Ohne Erklärung bleibt Wissen schwer übertragbar." }
      ]
    },
    {
      "id": 3,
      "name": "Technik-Team",
      "context": "Architektur-Review vor Implementierung",
      "need": "fachliche Tiefe, Randbedingungen und Trade-offs",
      "correctStyleId": "c",
      "styles": [
        { "id": "a", "label": "Allgemein & oberflächlich", "reason": "Zu wenig Substanz für ein technisches Review." },
        { "id": "b", "label": "Storytelling ohne technische Details", "reason": "Hilft beim Einstieg, ersetzt aber keine Architekturargumente." },
        { "id": "c", "label": "Detailliert & technisch", "reason": "Richtig: das Team braucht konkrete technische Entscheidungsgrundlagen." }
      ]
    }
  ]
}
