{
  "meta": {
    "topic": "Layered Architecture",
    "mechanic": "simulation",
    "engine": "SimulationGame",
    "variant": "layered_architecture",
    "version": "1.0"
  },
  "title": "Layered Architecture - Parameter Simulation",
  "goal": {
    "targetRateEur": 587,
    "maxDownPaymentEur": 1200
  },
  "pricing": {
    "baseRate": 571,
    "termPerMonthDiscount": 1.1,
    "downPaymentPer100Discount": 2.5,
    "kmPer1000Surcharge": 13,
    "minRate": 214
  },
  "limits": {
    "termMonths": {
      "min": 12,
      "max": 60,
      "step": 6,
      "default": 30
    },
    "downPaymentEur": {
      "min": 0,
      "max": 5700,
      "step": 100,
      "default": 1300
    },
    "kmPerYear": {
      "min": 8000,
      "max": 50000,
      "step": 1000,
      "default": 22000
    }
  }
}
