{
  "c_suite_explanations": {
    "self_titel": "Ergonomierichtlinien",
    "self_subtitel": "Gesund und leistungsfaehig arbeiten",
    "self_message": "Hi, ich bin Ergonomierichtlinien. Ich reduziere gesundheitliche Belastungen durch passende Arbeitsplatzgestaltung und nachhaltige Arbeitsroutinen.",
    "ceo_message": "Beim Thema Ergonomierichtlinien bewerte ich direkte Auswirkungen auf Positionierung und Wettbewerbsfaehigkeit.",
    "cfo_message": "Beim Thema Ergonomierichtlinien bewerte ich Preis- und Kostenwirkung sowie die Robustheit der Annahmen.",
    "coo_message": "Beim Thema Ergonomierichtlinien pruefe ich Auswirkungen auf Kapazitaeten, Prozessdesign und operative Planbarkeit.",
    "chro_message": "Beim Thema Ergonomierichtlinien muessen Rollenbilder, Kompetenzen und Arbeitsmodelle passend weiterentwickelt werden.",
    "cmo_message": "Beim Thema Ergonomierichtlinien steuere ich Angebotsdifferenzierung und kundengerechte Kommunikation.",
    "cro_message": "Beim Thema Ergonomierichtlinien bewerte ich Markt- und Regulierungsrisiken mit fruehen Indikatoren."
  }
}
