{
  "meta": {
    "topic": "Duales System",
    "mechanic": "matching_pairs",
    "engine": "MatchingGame",
    "variant": "duales_system",
    "source": "_gg98_decision_game.json",
    "version": "1.1"
  },
  "metadata": {
    "title": "Duales System - Zuordnen"
  },
  "levels": [
    {
      "id": 1,
      "title": "Duales System - Szenario-Zuordnung",
      "description": "Verbinde jedes Szenario mit der passenden Entscheidung und der Begruendung.",
      "pairs": [
        {
          "left": "Szenario 1: Welche Priorisierung ist bei knappen Fristen zuerst sinnvoll? Faellige Hochrisiko-Tickets zuerst.",
          "right": "Passende Entscheidung 1: Hochprioritaets-Ticket mit naher Faelligkeit zuerst"
        },
        {
          "left": "Begruendung 1: Runde 1",
          "right": "Warum passend 1: Richtig. Das minimiert Fristschaden."
        },
        {
          "left": "Szenario 2: Welche KPI gehoert zum Stresstest laut Plan? Trefferquote plus Queue-Last.",
          "right": "Passende Entscheidung 2: Fristtrefferquote und Warteschlangenlaenge"
        },
        {
          "left": "Begruendung 2: Runde 2",
          "right": "Warum passend 2: Genau. Beide KPI sind vorgesehen."
        },
        {
          "left": "Szenario 3: Wann entsteht ein Zusatzabzug? Kritisches Ticket ueber Faelligkeit.",
          "right": "Passende Entscheidung 3: Wenn ein Hochprioritaets-Ticket ueberfaellig wird"
        },
        {
          "left": "Begruendung 3: Runde 3",
          "right": "Warum passend 3: Richtig. Das wird strenger geahndet."
        },
        {
          "left": "Szenario 4: Welche Zielmarke aktiviert laut Plan einen Bonus? Konstant hohe Trefferquote.",
          "right": "Passende Entscheidung 4: Trefferquote ueber 85 Prozent ueber mehrere Runden"
        },
        {
          "left": "Begruendung 4: Runde 4",
          "right": "Warum passend 4: Richtig. Konstanz wird belohnt."
        }
      ]
    }
  ]
}
