{
  "c_suite_explanations": {
    "self_titel": "SAN",
    "self_subtitel": "Blockbasierter Storage im Netzwerk",
    "self_message": "Hi, ich bin SAN. Ich biete performanten Blockspeicher fuer Server-Workloads mit Fokus auf Verfuegbarkeit und I/O.",
    "cio_message": "SAN ist Teil des digitalen Rueckgrats fuer Verfuegbarkeit und Servicequalitaet.",
    "cto_message": "Bei SAN sind Architektur und Plattformwahl entscheidend fuer Skalierung und Performance.",
    "coo_message": "SAN braucht belastbare Betriebsprozesse, Redundanz und schnelle Wiederanlaufwege.",
    "cfo_message": "SAN wird ueber TCO bewertet: Anschaffung, Betrieb, Energie und Ausfallkosten zusammen.",
    "ciso_message": "SAN verlangt kontrollierte Zugriffe, Härtung und Integritaetsschutz im Infrastrukturstack.",
    "cro_message": "SAN reduziert Risiko nur, wenn SPOFs, Backups und Recovery real getestet sind."
  }
}
