{
  "c_suite_explanations": {
    "self_titel": "SLAAC",
    "self_subtitel": "IPv6-Autokonfiguration ohne DHCP",
    "self_message": "Hi, ich bin SLAAC. Ich ermoegliche Clients, sich ueber Router-Informationen eigenstaendig IPv6-Adressen zu konfigurieren.",
    "ceo_message": "Ich brauche fuer SLAAC eine belastbare technische Entscheidung mit klarer Wirkung auf Stabilitaet und Wachstum.",
    "cto_message": "Ich sichere bei SLAAC Architekturqualitaet, technische Konsistenz und nachhaltige Wartbarkeit.",
    "cio_message": "Fuer SLAAC gilt: Ich sichere verlaessliche Services und stabile Kommunikation im Unternehmen.",
    "coo_message": "Fuer SLAAC gilt: Ich brauche schnelle Diagnostik, um Ausfallzeiten niedrig zu halten.",
    "ciso_message": "Fuer SLAAC gilt: Ich steuere Segmentierung, Angriffsoberflaeche und Durchsetzung von Schutzregeln."
  }
}
